{
  "date": "2026-03-08",
  "updated_at": "2026-03-08 15:15",
  "naver_updated_at": "2026-03-08 15:15",
  "youtube_updated_at": "2026-03-08 15:15",
  "topics": [
    {
      "keyword": "질환",
      "score": 116.5,
      "verdict": "now",
      "n": 30,
      "t": 30,
      "w": 25,
      "r": 1.37,
      "change_rate": 127.4,
      "intent_type": "의심/경고형",
      "pharma_keywords": [
        "처방",
        "성분",
        "부작용",
        "대사",
        "약물"
      ],
      "g_total": 23499987,
      "g_expert": 207179,
      "g_label": "전문가 갭 큼",
      "news_count": 16,
      "news_headlines": [
        {
          "title": "정선군민 의료 혜택 넓어진다, 정선군립병원, 중앙대병원 방문 진료 과...",
          "link": "https://n.news.naver.com/mnews/article/087/0001178567?sid=102"
        },
        {
          "title": "강원 성인 비만율 전국 상위 수준…수도권역 1위 철원",
          "link": "https://n.news.naver.com/mnews/article/087/0001178504?sid=102"
        }
      ],
      "ai_summary": "",
      "title_idea": "",
      "target_reader": ""
    },
    {
      "keyword": "호흡기 질환",
      "score": 57.0,
      "verdict": "hot",
      "n": 30,
      "t": 15,
      "w": 5,
      "r": 1.14,
      "change_rate": 23.6,
      "intent_type": "구매/추천형",
      "pharma_keywords": [
        "성분"
      ],
      "g_total": 1155731,
      "g_expert": 8411,
      "g_label": "전문가 갭 큼",
      "news_count": 3,
      "news_headlines": [
        {
          "title": "식약처 &quot;의료용 흡입기 위생관리 철저히 해야&quot;",
          "link": "http://www.ujeil.com/news/articleView.html?idxno=382194"
        },
        {
          "title": "대구시교육청,'냉·난방기종합세척' 3년간 68억 투입",
          "link": "https://www.dkilbo.com/news/articleView.html?idxno=536195"
        }
      ],
      "ai_summary": "",
      "title_idea": "",
      "target_reader": ""
    },
    {
      "keyword": "심혈관질환 전조증상",
      "score": 56.0,
      "verdict": "hot",
      "n": 40,
      "t": 0,
      "w": 0,
      "r": 1.4,
      "change_rate": -11.5,
      "intent_type": "의심/경고형",
      "pharma_keywords": [
        "성분",
        "부작용",
        "대사",
        "약물"
      ],
      "g_total": 20649,
      "g_expert": 262,
      "g_label": "전문가 갭 큼",
      "news_count": 0,
      "news_headlines": [
        {
          "title": "“김수용처럼 주름 있으면 뇌졸중 온다고?”…“미신이야” 선 그은 교...",
          "link": "https://n.news.naver.com/mnews/article/016/0002610131?sid=103"
        },
        {
          "title": "3월 환절기에 꽃샘추위와 미세먼지…치명적 심혈관계 건강 위협",
          "link": "https://www.koreahealthlog.com/news/articleView.html?idxno=56157"
        }
      ],
      "parent": "질환",
      "ai_summary": "",
      "title_idea": "",
      "target_reader": ""
    },
    {
      "keyword": "비만 호르몬",
      "score": 56.0,
      "verdict": "hot",
      "n": 40,
      "t": 0,
      "w": 0,
      "r": 1.4,
      "change_rate": 0,
      "intent_type": "의심/경고형",
      "pharma_keywords": [
        "처방",
        "성분",
        "부작용",
        "대사",
        "약물"
      ],
      "g_total": 848187,
      "g_expert": 7643,
      "g_label": "전문가 갭 큼",
      "news_count": 0,
      "news_headlines": [
        {
          "title": "수면 부족, 대사질환 위험 키운다",
          "link": "https://www.insnews.co.kr/news/articleView.html?idxno=89439"
        },
        {
          "title": "‘근육서 조혈호르몬 EPO 생성’ 세계 첫 규명",
          "link": "http://www.kjdaily.com/article.php?aid=1772965286674458062"
        }
      ],
      "parent": "비만",
      "ai_summary": "",
      "title_idea": "",
      "target_reader": ""
    },
    {
      "keyword": "비만",
      "score": 55.8,
      "verdict": "hot",
      "n": 5,
      "t": 10,
      "w": 30,
      "r": 1.24,
      "change_rate": 7.5,
      "intent_type": "구매/추천형",
      "pharma_keywords": [
        "대사",
        "약물"
      ],
      "g_total": 5306688,
      "g_expert": 34272,
      "g_label": "전문가 갭 큼",
      "news_count": 35,
      "news_headlines": [
        {
          "title": "강원 성인 비만율 전국 상위 수준…수도권역 1위 철원",
          "link": "https://n.news.naver.com/mnews/article/087/0001178504?sid=102"
        },
        {
          "title": "수면 부족, 대사질환 위험 키운다",
          "link": "https://www.insnews.co.kr/news/articleView.html?idxno=89439"
        }
      ],
      "aliases": [
        "비만 운동"
      ],
      "ai_summary": "",
      "title_idea": "",
      "target_reader": ""
    },
    {
      "keyword": "알레르기나 호흡기",
      "score": 55.2,
      "verdict": "hot",
      "n": 40,
      "t": 0,
      "w": 0,
      "r": 1.38,
      "change_rate": 0,
      "intent_type": "의심/경고형",
      "pharma_keywords": [
        "처방",
        "용량",
        "성분",
        "부작용",
        "대사"
      ],
      "g_total": 610474,
      "g_expert": 7215,
      "g_label": "전문가 갭 큼",
      "news_count": 0,
      "news_headlines": [
        {
          "title": "'두쫀쿠' 먹다 알레르기에 치아 손상까지…",
          "link": "https://www.idaegu.co.kr/news/articleView.html?idxno=540952"
        },
        {
          "title": "두쫀쿠 먹고 두드러기, 치아 부러져…안전 정보 '깜깜이'에 피해 쏟아져",
          "link": "https://n.news.naver.com/mnews/article/008/0005326871?sid=102"
        }
      ],
      "parent": "호흡기 질환",
      "ai_summary": "",
      "title_idea": "",
      "target_reader": ""
    },
    {
      "keyword": "비만치료제 위고비",
      "score": 54.0,
      "verdict": "hot",
      "n": 40,
      "t": 0,
      "w": 0,
      "r": 1.35,
      "change_rate": 0,
      "intent_type": "중립",
      "pharma_keywords": [
        "처방",
        "금기",
        "성분",
        "부작용",
        "대사",
        "약물"
      ],
      "g_total": 51999,
      "g_expert": 1575,
      "g_label": "전문가 갭 큼",
      "news_count": 0,
      "news_headlines": [
        {
          "title": "비만치료제 ‘경구용’으로 기술력 이동… 국내서도 ‘가격 경쟁’ 불가...",
          "link": "https://n.news.naver.com/mnews/article/029/0003014478?sid=105"
        },
        {
          "title": "출시 앞둔 궁극의 다이어트 치료제, 위고비 대신할 ‘이것’",
          "link": "https://www.gqkorea.co.kr/2026/03/08/%ec%b6%9c%ec%8b%9c-%ec%95%9e%eb%91%94-%ea%b6%81%ea%b7%b9%ec%9d%98-%eb%8b%a4%ec%9d%b4%ec%96%b4%ed%8a%b8-%ec%b9%98%eb%a3%8c%ec%a0%9c-%ec%9c%84%ea%b3%a0%eb%b9%84-%eb%8c%80%ec%8b%a0%ed%95%a0-%ec%9d%b4/?utm_source=naver&utm_medium=partnership"
        }
      ],
      "parent": "치료제",
      "aliases": [
        "치료제",
        "위고비"
      ],
      "ai_summary": "",
      "title_idea": "",
      "target_reader": ""
    },
    {
      "keyword": "면역질환 신체",
      "score": 52.5,
      "verdict": "hot",
      "n": 30,
      "t": 0,
      "w": 5,
      "r": 1.5,
      "change_rate": 0,
      "intent_type": "의심/경고형",
      "pharma_keywords": [
        "처방",
        "부작용",
        "대사",
        "약물"
      ],
      "g_total": 1118190,
      "g_expert": 10268,
      "g_label": "전문가 갭 큼",
      "news_count": 3,
      "news_headlines": [
        {
          "title": "고성군 해양치유센터, 복합 치유 공간 거점 도약 예약",
          "link": "http://www.gnmaeil.com/news/articleView.html?idxno=581959"
        },
        {
          "title": "목은 안 아픈데 고열·황달이?... 20대 대학생의 ‘가짜 감기’ 정체는...",
          "link": "https://n.news.naver.com/mnews/article/296/0000098305?sid=103"
        }
      ],
      "ai_summary": "",
      "title_idea": "",
      "target_reader": ""
    },
    {
      "keyword": "잇몸 질환",
      "score": 50.0,
      "verdict": "hot",
      "n": 30,
      "t": 5,
      "w": 5,
      "r": 1.25,
      "change_rate": 3.2,
      "intent_type": "중립",
      "pharma_keywords": [
        "성분"
      ],
      "g_total": 2470819,
      "g_expert": 10366,
      "g_label": "전문가 갭 큼",
      "news_count": 3,
      "news_headlines": [
        {
          "title": "&quot;아침에 이불 털지 마세요… '세균·진드기·각질 주스' 마시는 꼴&quot; ('대...",
          "link": "https://m.entertain.naver.com/article/213/0001376529"
        },
        {
          "title": "구강 세균이 부른 전신 질환의 경고… 뇌경색부터 암 위험까지 ('대단한...",
          "link": "https://m.entertain.naver.com/article/445/0000389653"
        }
      ],
      "ai_summary": "",
      "title_idea": "",
      "target_reader": ""
    },
    {
      "keyword": "여러 면역질환",
      "score": 49.7,
      "verdict": "hot",
      "n": 30,
      "t": 0,
      "w": 5,
      "r": 1.42,
      "change_rate": 0,
      "intent_type": "의심/경고형",
      "pharma_keywords": [
        "성분",
        "대사",
        "약물"
      ],
      "g_total": 1229236,
      "g_expert": 16401,
      "g_label": "전문가 갭 큼",
      "news_count": 3,
      "news_headlines": [
        {
          "title": "'알부민' 열풍에 의사들 &quot;비윤리적 의사의 혹세무민&quot;…비판 이유는",
          "link": "https://n.news.naver.com/mnews/article/053/0000056445?sid=103"
        },
        {
          "title": "음식 알레르기 방심하면 큰 위험…원인 식품부터 찾아야",
          "link": "http://www.kwangju.co.kr/article.php?aid=1772966700796390025"
        }
      ],
      "ai_summary": "",
      "title_idea": "",
      "target_reader": ""
    },
    {
      "keyword": "심각 질환",
      "score": 49.2,
      "verdict": "hot",
      "n": 40,
      "t": 0,
      "w": 0,
      "r": 1.23,
      "change_rate": 0,
      "intent_type": "구매/추천형",
      "pharma_keywords": [
        "금기",
        "부작용",
        "대사"
      ],
      "g_total": 27435,
      "g_expert": 1147,
      "g_label": "전문가 부족",
      "news_count": 0,
      "news_headlines": [
        {
          "title": "[충남시론] 대기오염의 인명 피해가 갈수록 심각해진다",
          "link": "http://www.chungnamilbo.co.kr/news/articleView.html?idxno=876686"
        },
        {
          "title": "[세계 여성의 날] 여성 삶의 질 저하하는 자궁근종·자궁내막증·만성골...",
          "link": "https://n.news.naver.com/mnews/article/396/0000737532?sid=103"
        }
      ],
      "parent": "질환",
      "ai_summary": "",
      "title_idea": "",
      "target_reader": ""
    },
    {
      "keyword": "심혈관 질환",
      "score": 48.6,
      "verdict": "hot",
      "n": 30,
      "t": 0,
      "w": 5,
      "r": 1.39,
      "change_rate": -10.9,
      "intent_type": "의심/경고형",
      "pharma_keywords": [
        "성분",
        "함량",
        "부작용",
        "대사",
        "약물"
      ],
      "g_total": 1733322,
      "g_expert": 19767,
      "g_label": "전문가 갭 큼",
      "news_count": 3,
      "news_headlines": [
        {
          "title": "정선군민 의료 혜택 넓어진다, 정선군립병원, 중앙대병원 방문 진료 과...",
          "link": "https://n.news.naver.com/mnews/article/087/0001178567?sid=102"
        },
        {
          "title": "뇌건강 저해 초미세먼지의 신경독성 기전 규명",
          "link": "https://www.ksilbo.co.kr/news/articleView.html?idxno=1050779"
        }
      ],
      "ai_summary": "",
      "title_idea": "",
      "target_reader": ""
    },
    {
      "keyword": "감리비 받고",
      "score": 47.2,
      "verdict": "hot",
      "n": 40,
      "t": 0,
      "w": 0,
      "r": 1.18,
      "change_rate": 0,
      "intent_type": "구매/추천형",
      "pharma_keywords": [],
      "g_total": 3557,
      "g_expert": 4,
      "g_label": "전문가 갭 큼",
      "news_count": 0,
      "news_headlines": [
        {
          "title": "멕시카나치킨, 불확실한 창업시장 속 '수익성과 지속성' 해법 제시",
          "link": "https://n.news.naver.com/mnews/article/030/0003402167?sid=101"
        },
        {
          "title": "두레통닭, 2026년 신규매장 김해 장유점·서충주점 오픈…‘창업지원 확...",
          "link": "https://www.siminilbo.co.kr/news/newsview.php?ncode=1160291167203681"
        }
      ],
      "parent": "비만",
      "ai_summary": "",
      "title_idea": "",
      "target_reader": ""
    },
    {
      "keyword": "대사질환 치료제",
      "score": 45.9,
      "verdict": "hot",
      "n": 30,
      "t": 0,
      "w": 5,
      "r": 1.31,
      "change_rate": 0,
      "intent_type": "의심/경고형",
      "pharma_keywords": [
        "처방",
        "용량",
        "성분",
        "부작용",
        "약동학",
        "대사",
        "약물"
      ],
      "g_total": 97806,
      "g_expert": 6285,
      "g_label": "전문가 부족",
      "news_count": 3,
      "news_headlines": [
        {
          "title": "‘근육서 조혈호르몬 EPO 생성’ 세계 첫 규명",
          "link": "http://www.kjdaily.com/article.php?aid=1772965286674458062"
        },
        {
          "title": "출시 앞둔 궁극의 다이어트 치료제, 위고비 대신할 ‘이것’",
          "link": "https://www.gqkorea.co.kr/2026/03/08/%ec%b6%9c%ec%8b%9c-%ec%95%9e%eb%91%94-%ea%b6%81%ea%b7%b9%ec%9d%98-%eb%8b%a4%ec%9d%b4%ec%96%b4%ed%8a%b8-%ec%b9%98%eb%a3%8c%ec%a0%9c-%ec%9c%84%ea%b3%a0%eb%b9%84-%eb%8c%80%ec%8b%a0%ed%95%a0-%ec%9d%b4/?utm_source=naver&utm_medium=partnership"
        }
      ],
      "ai_summary": "",
      "title_idea": "",
      "target_reader": ""
    },
    {
      "keyword": "여드름 치료제",
      "score": 45.1,
      "verdict": "hot",
      "n": 30,
      "t": 0,
      "w": 5,
      "r": 1.29,
      "change_rate": -36.6,
      "intent_type": "의심/경고형",
      "pharma_keywords": [
        "처방",
        "복용법",
        "성분",
        "함량",
        "부작용",
        "약물"
      ],
      "g_total": 98813,
      "g_expert": 6706,
      "g_label": "전문가 부족",
      "news_count": 3,
      "news_headlines": [
        {
          "title": "브리스톨 마이어스 스큅, 건선성 관절염 치료제 Sotyktu FDA 승인 획득",
          "link": "https://www.tokenpost.kr/news/tech/337037"
        },
        {
          "title": "지루성피부염, 가려움·각질·홍조부터 비듬·상열감까지 치료는 어떻게...",
          "link": "https://www.ibabynews.com/news/articleView.html?idxno=149349"
        }
      ],
      "ai_summary": "",
      "title_idea": "",
      "target_reader": ""
    },
    {
      "keyword": "칠곡중앙대로 강북약국",
      "score": 44.5,
      "verdict": "warm",
      "n": 30,
      "t": 0,
      "w": 5,
      "r": 1.27,
      "change_rate": 0,
      "intent_type": "의심/경고형",
      "pharma_keywords": [
        "처방",
        "복용법",
        "부작용"
      ],
      "g_total": 3429,
      "g_expert": 296,
      "g_label": "전문가 부족",
      "news_count": 3,
      "news_headlines": [
        {
          "title": "대구 연중무휴 심야·자정약국 12개소 운영",
          "link": "https://n.news.naver.com/mnews/article/469/0000862573?sid=102"
        },
        {
          "title": "심야약국 및 365일 운영 약국",
          "link": "//www.yeongnam.com/web/view.php?key=20200124010004211"
        }
      ],
      "ai_summary": "",
      "title_idea": "",
      "target_reader": ""
    },
    {
      "keyword": "약국",
      "score": 44.0,
      "verdict": "warm",
      "n": 0,
      "t": 10,
      "w": 30,
      "r": 1.1,
      "change_rate": 10.6,
      "intent_type": "구매/추천형",
      "pharma_keywords": [
        "처방",
        "복용법",
        "성분",
        "부작용",
        "약물"
      ],
      "g_total": 3659316,
      "g_expert": 459446,
      "g_label": "보통",
      "news_count": 48,
      "news_headlines": [
        {
          "title": "[발언대]“사무장병원(약국) 특사경 제도 도입, 불법의료기관 이제는 사...",
          "link": "https://n.news.naver.com/mnews/article/087/0001178463?sid=102"
        },
        {
          "title": "[발언대]사무장병원 ‘사후 환수’에서 ‘사전 예방’으로 전환해야",
          "link": "https://n.news.naver.com/mnews/article/087/0001178458?sid=102"
        }
      ],
      "aliases": [
        "약사"
      ],
      "ai_summary": "",
      "title_idea": "",
      "target_reader": ""
    },
    {
      "keyword": "치료제 아닌",
      "score": 42.4,
      "verdict": "warm",
      "n": 30,
      "t": 0,
      "w": 5,
      "r": 1.21,
      "change_rate": 0,
      "intent_type": "구매/추천형",
      "pharma_keywords": [
        "처방",
        "복용법",
        "용량",
        "성분",
        "부작용",
        "약물"
      ],
      "g_total": 286342,
      "g_expert": 13396,
      "g_label": "전문가 부족",
      "news_count": 3,
      "news_headlines": [
        {
          "title": "제약바이오협회, 약가인하가 혁신 만든다는 주장에 반박…연구개발 촉...",
          "link": "https://www.medigatenews.com/news/2038878756"
        },
        {
          "title": "대구한의대, 국내 최초 '동물보건학 박사' 배출",
          "link": "http://www.hidomin.com/news/articleView.html?idxno=611481"
        }
      ],
      "ai_summary": "",
      "title_idea": "",
      "target_reader": ""
    },
    {
      "keyword": "탈모 치료제",
      "score": 42.4,
      "verdict": "warm",
      "n": 30,
      "t": 0,
      "w": 5,
      "r": 1.21,
      "change_rate": -32.8,
      "intent_type": "구매/추천형",
      "pharma_keywords": [
        "처방",
        "용량",
        "성분",
        "부작용",
        "약동학",
        "대사",
        "약물"
      ],
      "g_total": 116930,
      "g_expert": 6668,
      "g_label": "전문가 부족",
      "news_count": 3,
      "news_headlines": [
        {
          "title": "인벤티지랩. 비만·탈모까지 '장기지속형 주사제' 확장",
          "link": "https://n.news.naver.com/mnews/article/009/0005646791?sid=103"
        },
        {
          "title": "케미컬 의약품: 화학합성으로 만드는 '저분자 약'의 기본[제약바이오 해...",
          "link": "https://www.newsway.co.kr/news/view?ud=2026030611364680869"
        }
      ],
      "ai_summary": "",
      "title_idea": "",
      "target_reader": ""
    },
    {
      "keyword": "중단",
      "score": 39.9,
      "verdict": "warm",
      "n": 5,
      "t": 0,
      "w": 25,
      "r": 1.33,
      "change_rate": -4.6,
      "intent_type": "의심/경고형",
      "pharma_keywords": [
        "부작용"
      ],
      "g_total": 8410953,
      "g_expert": 86133,
      "g_label": "전문가 갭 큼",
      "news_count": 16,
      "news_headlines": [
        {
          "title": "속초시, 3월 눈·비로 겨울 가뭄·산불 걱정 덜었다",
          "link": "https://n.news.naver.com/mnews/article/087/0001178585?sid=102"
        },
        {
          "title": "통합특별시 '사령탑' 가닥, '감시탑' 안갯속",
          "link": "http://www.gjdream.com/news/articleView.html?idxno=667674"
        }
      ],
      "ai_summary": "",
      "title_idea": "",
      "target_reader": ""
    },
    {
      "keyword": "릴리",
      "score": 39.3,
      "verdict": "warm",
      "n": 5,
      "t": 10,
      "w": 15,
      "r": 1.31,
      "change_rate": 9.0,
      "intent_type": "구매/추천형",
      "pharma_keywords": [
        "처방",
        "용량",
        "부작용",
        "약물"
      ],
      "g_total": 824268,
      "g_expert": 2722,
      "g_label": "전문가 갭 큼",
      "news_count": 16,
      "news_headlines": [
        {
          "title": "신인 대거 합류한 ‘LPGA 장타 랭킹’ 요동…‘김아림 4위→26위’ ‘윤...",
          "link": "https://m.sports.naver.com/golf/article/011/0004596958"
        },
        {
          "title": "20세기 유럽 바이올린 소나타의 정수 선봬",
          "link": "https://www.ksmnews.co.kr/news/view.php?idx=593407"
        }
      ],
      "ai_summary": "",
      "title_idea": "",
      "target_reader": ""
    },
    {
      "keyword": "맞춤형",
      "score": 38.9,
      "verdict": "warm",
      "n": 5,
      "t": 15,
      "w": 15,
      "r": 1.11,
      "change_rate": 28.8,
      "intent_type": "구매/추천형",
      "pharma_keywords": [],
      "g_total": 16554464,
      "g_expert": 35054,
      "g_label": "전문가 갭 큼",
      "news_count": 15,
      "news_headlines": [
        {
          "title": "‘2주 재활→어깨 수술 여부 결정’ 김광현, 설마 시즌아웃 위기? “컨...",
          "link": "https://m.sports.naver.com/kbaseball/article/109/0005490149"
        },
        {
          "title": "속초시 노학동, 민·관 협력으로 복지사각지대 촘촘히 메운다",
          "link": "https://n.news.naver.com/mnews/article/087/0001178570?sid=102"
        }
      ],
      "ai_summary": "",
      "title_idea": "",
      "target_reader": ""
    },
    {
      "keyword": "영양제",
      "score": 36.6,
      "verdict": "warm",
      "n": 5,
      "t": 5,
      "w": 20,
      "r": 1.22,
      "change_rate": 2.0,
      "intent_type": "구매/추천형",
      "pharma_keywords": [
        "처방",
        "상호작용",
        "성분",
        "함량",
        "부작용",
        "약물"
      ],
      "g_total": 4829968,
      "g_expert": 191378,
      "g_label": "전문가 부족",
      "news_count": 33,
      "news_headlines": [
        {
          "title": "서울 중구, 취약계층 반려동물 진료비 최대 40만 원 지원",
          "link": "https://n.news.naver.com/mnews/article/011/0004596969?sid=102"
        },
        {
          "title": "'사랑처방' 김승수 가족, 이사 결심했는데…김형묵 &quot;안돼&quot;[종합]",
          "link": "http://www.celuvmedia.com/article.php?aid=1772973095516197006"
        }
      ],
      "ai_summary": "",
      "title_idea": "",
      "target_reader": ""
    },
    {
      "keyword": "스테키마",
      "score": 30.0,
      "verdict": "warm",
      "n": 5,
      "t": 0,
      "w": 15,
      "r": 1.5,
      "change_rate": 0,
      "intent_type": "의심/경고형",
      "pharma_keywords": [
        "처방",
        "용량",
        "성분"
      ],
      "g_total": 2090,
      "g_expert": 24,
      "g_label": "전문가 갭 큼",
      "news_count": 19,
      "news_headlines": [
        {
          "title": "셀트리온, '스테키마' 52주 임상 결과 발표 ... 국제 피부과 학술지 게재",
          "link": "http://www.thefirstmedia.net/news/articleView.html?idxno=194936"
        },
        {
          "title": "셀트리온 ‘스테키마’ 52주 임상 결과 국제 피부과 학술지 게재",
          "link": "https://n.news.naver.com/mnews/article/029/0003014360?sid=105"
        }
      ],
      "ai_summary": "",
      "title_idea": "",
      "target_reader": ""
    },
    {
      "keyword": "올포글리프론",
      "score": 27.0,
      "verdict": "warm",
      "n": 5,
      "t": 0,
      "w": 15,
      "r": 1.35,
      "change_rate": 0,
      "intent_type": "중립",
      "pharma_keywords": [
        "처방",
        "성분",
        "부작용",
        "반감기",
        "대사",
        "약물"
      ],
      "g_total": 371,
      "g_expert": 4,
      "g_label": "전문가 갭 큼",
      "news_count": 19,
      "news_headlines": [
        {
          "title": "바이엘 코리아, 세계 여성의 날 맞아 여성 건강 인식 개선 캠페인 진행...",
          "link": "http://www.newsmp.com/news/articleView.html?idxno=251995"
        },
        {
          "title": "릴리 '올포글리프론', 리벨서스 대비 혈당 조절 및 체중 감소 개선 확인",
          "link": "https://www.kpanews.co.kr/news/articleView.html?idxno=530532"
        }
      ],
      "ai_summary": "",
      "title_idea": "",
      "target_reader": ""
    },
    {
      "keyword": "감량",
      "score": 26.6,
      "verdict": "warm",
      "n": 5,
      "t": 0,
      "w": 15,
      "r": 1.33,
      "change_rate": -4.5,
      "intent_type": "구매/추천형",
      "pharma_keywords": [
        "금기",
        "성분",
        "부작용",
        "대사"
      ],
      "g_total": 4473682,
      "g_expert": 24916,
      "g_label": "전문가 갭 큼",
      "news_count": 17,
      "news_headlines": [
        {
          "title": "안방 조형우, 뒷문 조병현, 선발 김건우… ‘2002년생 전성시대’ SSG, 추...",
          "link": "https://m.sports.naver.com/kbaseball/article/144/0001102079"
        },
        {
          "title": "갸름한 얼굴 이순실 맞아…&quot;이게 다 자본의 살이다&quot;",
          "link": "https://m.entertain.naver.com/article/003/0013808765"
        }
      ],
      "ai_summary": "",
      "title_idea": "",
      "target_reader": ""
    },
    {
      "keyword": "비만약",
      "score": 26.2,
      "verdict": "warm",
      "n": 0,
      "t": 0,
      "w": 20,
      "r": 1.31,
      "change_rate": -31.6,
      "intent_type": "구매/추천형",
      "pharma_keywords": [
        "처방",
        "성분",
        "부작용",
        "대사",
        "약물"
      ],
      "g_total": 47629,
      "g_expert": 1185,
      "g_label": "전문가 갭 큼",
      "news_count": 26,
      "news_headlines": [
        {
          "title": "비만치료제 ‘경구용’으로 기술력 이동… 국내서도 ‘가격 경쟁’ 불가...",
          "link": "https://n.news.naver.com/mnews/article/029/0003014478?sid=105"
        },
        {
          "title": "셀트리온, 바이오시밀러 최대실적 기반 '신약·비만약' 동시 공략",
          "link": "https://n.news.naver.com/mnews/article/009/0005646780?sid=103"
        }
      ],
      "ai_summary": "",
      "title_idea": "",
      "target_reader": ""
    },
    {
      "keyword": "다이어트",
      "score": 26.0,
      "verdict": "warm",
      "n": 0,
      "t": 0,
      "w": 20,
      "r": 1.3,
      "change_rate": -7.2,
      "intent_type": "중립",
      "pharma_keywords": [
        "성분",
        "부작용"
      ],
      "g_total": 20904195,
      "g_expert": 69914,
      "g_label": "전문가 갭 큼",
      "news_count": 54,
      "news_headlines": [
        {
          "title": "밀양시 삼랑진읍 주민자치 프로그램 개강",
          "link": "http://www.gnmaeil.com/news/articleView.html?idxno=581931"
        },
        {
          "title": "박진영 &quot;JYP와 이름 같아 '배달 사고' 나기도… 닭가슴살로 10㎏ 감량&quot; (...",
          "link": "https://m.entertain.naver.com/article/213/0001376574"
        }
      ],
      "ai_summary": "",
      "title_idea": "",
      "target_reader": ""
    },
    {
      "keyword": "건기식",
      "score": 24.6,
      "verdict": "pass",
      "n": 5,
      "t": 0,
      "w": 15,
      "r": 1.23,
      "change_rate": -20.3,
      "intent_type": "구매/추천형",
      "pharma_keywords": [
        "용량",
        "상호작용",
        "성분",
        "함량",
        "부작용",
        "약물"
      ],
      "g_total": 104516,
      "g_expert": 9542,
      "g_label": "전문가 부족",
      "news_count": 16,
      "news_headlines": [
        {
          "title": "[넥스트 올다무]① 처방 연고·상비약·영양제… 외국인 쇼핑코스 된 관...",
          "link": "https://n.news.naver.com/mnews/article/366/0001146630?sid=101"
        },
        {
          "title": "[아모레퍼시픽㊤] '글로벌리밸런싱'으로 '매출 5조원' 도전장",
          "link": "https://www.asiatime.co.kr/article/20260305500344"
        }
      ],
      "ai_summary": "",
      "title_idea": "",
      "target_reader": ""
    },
    {
      "keyword": "식약처",
      "score": 24.0,
      "verdict": "pass",
      "n": 0,
      "t": 0,
      "w": 20,
      "r": 1.2,
      "change_rate": -10.6,
      "intent_type": "구매/추천형",
      "pharma_keywords": [
        "복용법",
        "용량",
        "성분",
        "함량",
        "부작용",
        "대사"
      ],
      "g_total": 1864381,
      "g_expert": 66815,
      "g_label": "전문가 부족",
      "news_count": 26,
      "news_headlines": [
        {
          "title": "식약처 &quot;의료용 흡입기 위생관리 철저히 해야&quot;",
          "link": "http://www.ujeil.com/news/articleView.html?idxno=382194"
        },
        {
          "title": "'강아지 환영'이라더니…'이래서 장사하겠나' 사장님 한숨 [현장+]",
          "link": "https://n.news.naver.com/mnews/article/015/0005259608?sid=101"
        }
      ],
      "ai_summary": "",
      "title_idea": "",
      "target_reader": ""
    },
    {
      "keyword": "신약",
      "score": 23.6,
      "verdict": "pass",
      "n": 5,
      "t": 0,
      "w": 15,
      "r": 1.18,
      "change_rate": -14.4,
      "intent_type": "구매/추천형",
      "pharma_keywords": [],
      "g_total": 1423469,
      "g_expert": 25380,
      "g_label": "전문가 갭 큼",
      "news_count": 16,
      "news_headlines": [
        {
          "title": "강소 특구로 첨단연구 파이 키운 춘천시, 첫 광역 특구 전환 개척",
          "link": "https://n.news.naver.com/mnews/article/087/0001178465?sid=102"
        },
        {
          "title": "인류의 숙제 풀까...일본 '줄기세포' 세계 최초 승인·현대바이오 '뎅기...",
          "link": "https://n.news.naver.com/mnews/article/018/0006230475?sid=101"
        }
      ],
      "ai_summary": "",
      "title_idea": "",
      "target_reader": ""
    },
    {
      "keyword": "판매",
      "score": 22.6,
      "verdict": "pass",
      "n": 5,
      "t": 0,
      "w": 15,
      "r": 1.13,
      "change_rate": -8.8,
      "intent_type": "구매/추천형",
      "pharma_keywords": [
        "성분"
      ],
      "g_total": 58391825,
      "g_expert": 186408,
      "g_label": "전문가 갭 큼",
      "news_count": 19,
      "news_headlines": [
        {
          "title": "양종희, 여성 리더들과 한자리…&quot;AI시대 '공감 리더십'으로 가치 창출&quot;",
          "link": "https://www.apnews.kr/news/articleView.html?idxno=3046592"
        },
        {
          "title": "속초시, ‘2026 영랑호 벚꽃축제’ 판매부스 운영자 모집",
          "link": "https://n.news.naver.com/mnews/article/087/0001178572?sid=102"
        }
      ],
      "ai_summary": "",
      "title_idea": "",
      "target_reader": ""
    },
    {
      "keyword": "비만 치료제",
      "score": 19.7,
      "verdict": "pass",
      "n": 5,
      "t": 0,
      "w": 10,
      "r": 1.31,
      "change_rate": -40.4,
      "intent_type": "구매/추천형",
      "pharma_keywords": [
        "처방",
        "부작용",
        "대사",
        "약물"
      ],
      "g_total": 245383,
      "g_expert": 7018,
      "g_label": "전문가 갭 큼",
      "news_count": 0,
      "news_headlines": [
        {
          "title": "금융감독 패러다임 전환… '사전 예방' 중심으로",
          "link": "https://www.insnews.co.kr/news/articleView.html?idxno=89440"
        },
        {
          "title": "사상 최대 실적 찍은 동국제약···헬스케어·신약으로 '1조 매출' 겨냥",
          "link": "http://www.enewstoday.co.kr/news/articleView.html?idxno=2402823"
        }
      ],
      "parent": "치료제",
      "ai_summary": "",
      "title_idea": "",
      "target_reader": ""
    },
    {
      "keyword": "자가면역질환 치료제",
      "score": 18.8,
      "verdict": "pass",
      "n": 15,
      "t": 0,
      "w": 0,
      "r": 1.25,
      "change_rate": 0,
      "intent_type": "의심/경고형",
      "pharma_keywords": [
        "약동학",
        "약물"
      ],
      "g_total": 54349,
      "g_expert": 1813,
      "g_label": "전문가 부족",
      "news_count": 0,
      "news_headlines": [
        {
          "title": "아이엠바이오 청약 시작…코스모로보틱스 수요예측",
          "link": "https://n.news.naver.com/mnews/article/015/0005259553?sid=101"
        },
        {
          "title": "브리즈바이오, 다양한 장기에 나노입자 기반 약물 전달",
          "link": "https://n.news.naver.com/mnews/article/009/0005646814?sid=103"
        }
      ],
      "parent": "치료제",
      "ai_summary": "",
      "title_idea": "",
      "target_reader": ""
    },
    {
      "keyword": "공공심야약국",
      "score": 13.0,
      "verdict": "pass",
      "n": 0,
      "t": 0,
      "w": 20,
      "r": 0.65,
      "change_rate": -24.0,
      "intent_type": "구매/추천형",
      "pharma_keywords": [
        "처방",
        "대사"
      ],
      "g_total": 13157,
      "g_expert": 4403,
      "g_label": "전문가 포화",
      "news_count": 24,
      "news_headlines": [
        {
          "title": "구미시, 지역 소아 필수의료 안전망 완성",
          "link": "https://www.idaegu.co.kr/news/articleView.html?idxno=540959"
        },
        {
          "title": "구미시, 출생부터 재활까지 책임지는 ‘소아 의료 4대 축’ 완성",
          "link": "https://www.ksmnews.co.kr/news/view.php?idx=593821"
        }
      ],
      "ai_summary": "",
      "title_idea": "",
      "target_reader": ""
    },
    {
      "keyword": "비만 고혈압",
      "score": 7.0,
      "verdict": "pass",
      "n": 5,
      "t": 0,
      "w": 0,
      "r": 1.4,
      "change_rate": -6.1,
      "intent_type": "의심/경고형",
      "pharma_keywords": [
        "처방",
        "금기",
        "대사",
        "약물"
      ],
      "g_total": 791875,
      "g_expert": 8298,
      "g_label": "전문가 갭 큼",
      "news_count": 0,
      "news_headlines": [
        {
          "title": "수면 부족, 대사질환 위험 키운다",
          "link": "https://www.insnews.co.kr/news/articleView.html?idxno=89439"
        },
        {
          "title": "[지방소멸 대응 의성군의 도전과 변화] 언제나 '건강한 미소' 잃지 않도...",
          "link": "https://www.idaegu.co.kr/news/articleView.html?idxno=540955"
        }
      ],
      "parent": "비만",
      "ai_summary": "",
      "title_idea": "",
      "target_reader": ""
    },
    {
      "keyword": "치료제 개발",
      "score": 7.0,
      "verdict": "pass",
      "n": 5,
      "t": 0,
      "w": 0,
      "r": 1.4,
      "change_rate": 0,
      "intent_type": "의심/경고형",
      "pharma_keywords": [
        "용량",
        "성분",
        "부작용",
        "약물"
      ],
      "g_total": 750183,
      "g_expert": 17149,
      "g_label": "전문가 갭 큼",
      "news_count": 0,
      "news_headlines": [
        {
          "title": "인류의 숙제 풀까...일본 '줄기세포' 세계 최초 승인·현대바이오 '뎅기...",
          "link": "https://n.news.naver.com/mnews/article/018/0006230475?sid=101"
        },
        {
          "title": "혈당 잡는 고춧잎...산업화 '시동'",
          "link": "https://jtv.co.kr/2021/?c=3/45&uid=2201089"
        }
      ],
      "parent": "치료제",
      "ai_summary": "",
      "title_idea": "",
      "target_reader": ""
    },
    {
      "keyword": "유전자 치료제",
      "score": 6.7,
      "verdict": "pass",
      "n": 5,
      "t": 0,
      "w": 0,
      "r": 1.33,
      "change_rate": -33.1,
      "intent_type": "의심/경고형",
      "pharma_keywords": [
        "부작용",
        "약물"
      ],
      "g_total": 51257,
      "g_expert": 1499,
      "g_label": "전문가 갭 큼",
      "news_count": 0,
      "news_headlines": [
        {
          "title": "‘근육서 조혈호르몬 EPO 생성’ 세계 첫 규명",
          "link": "http://www.kjdaily.com/article.php?aid=1772965286674458062"
        },
        {
          "title": "전이성 유방암, 생존율 떨어지는데 2차 치료 문턱도 높아",
          "link": "http://www.mkhealth.co.kr/news/articleView.html?idxno=77851"
        }
      ],
      "parent": "치료제",
      "ai_summary": "",
      "title_idea": "",
      "target_reader": ""
    }
  ],
  "pharma_news": [
    {
      "title": "약가제도 개정안 잠시 멈춘 사이 바이오 공모주는 '물 올라'",
      "link": "https://www.hitnews.co.kr/news/articleView.html?idxno=74395",
      "pub_date": "Sat, 07 Mar 2026 06:12:00 +0900",
      "signal": "normal",
      "trigger": "약가"
    },
    {
      "title": "수면질환 치료제 '코리아 패싱' 우려…약가 장벽에 막힌 치료",
      "link": "https://www.medipana.com/news/articleView.html?idxno=407841",
      "pub_date": "Sat, 07 Mar 2026 06:06:00 +0900",
      "signal": "normal",
      "trigger": "약가"
    },
    {
      "title": "&quot;'수면장애' 급여 미적용과 '코리아 패싱'으로 사각 지대&quot;",
      "link": "https://www.bosa.co.kr/news/articleView.html?idxno=3000088",
      "pub_date": "Sat, 07 Mar 2026 06:00:00 +0900",
      "signal": "normal",
      "trigger": "급여"
    },
    {
      "title": "대원디아제팜2mg 8월말 공급중단…탈제나·레스콜엑스도 7월까지",
      "link": "https://www.kpanews.co.kr/news/articleView.html?idxno=530502",
      "pub_date": "Fri, 06 Mar 2026 12:06:00 +0900",
      "signal": "strong",
      "trigger": "공급중단"
    },
    {
      "title": "애경산업, 치약 금지 성분 검출에도 회수율 8%에 그쳐",
      "link": "https://mdtoday.co.kr/news/view/1065576202397210",
      "pub_date": "Thu, 05 Mar 2026 10:40:00 +0900",
      "signal": "strong",
      "trigger": "회수"
    },
    {
      "title": "베트남, '금지성분' 함유 화장품 291종 리콜…韓브랜드 포함",
      "link": "https://www.insidevina.com/news/articleView.html?idxno=42650",
      "pub_date": "Thu, 05 Mar 2026 09:16:00 +0900",
      "signal": "strong",
      "trigger": "리콜"
    },
    {
      "title": "스킨부스터 광풍속 환자안전 실종…뚫려버린 규제 사각지대",
      "link": "https://www.medicaltimes.com/Main/News/NewsView.html?ID=1167536&ref=naverpc",
      "pub_date": "Thu, 05 Mar 2026 05:30:00 +0900",
      "signal": "normal",
      "trigger": "규제"
    },
    {
      "title": "[단독] 애경 ‘금지성분 중국산 치약’ 회수율 8% 그쳐… 뒷감당은 태광...",
      "link": "https://n.news.naver.com/mnews/article/029/0003013718?sid=101",
      "pub_date": "Wed, 04 Mar 2026 11:31:00 +0900",
      "signal": "strong",
      "trigger": "회수"
    },
    {
      "title": "태광-애경, 225억 깎고 한 달 더 끌었다…'2080 리콜'이 바꾼 인수 조건",
      "link": "https://www.bizhankook.com/bk/article/31545",
      "pub_date": "Fri, 20 Feb 2026 20:00:00 +0900",
      "signal": "strong",
      "trigger": "리콜"
    },
    {
      "title": "태광산업, '치약 리콜 사태' 애경산업 인수가 낮춰",
      "link": "http://www.newsfc.co.kr/news/articleView.html?idxno=76879",
      "pub_date": "Fri, 20 Feb 2026 14:42:00 +0900",
      "signal": "strong",
      "trigger": "리콜"
    },
    {
      "title": "&quot;압타밀의 역설&quot;…유럽 리콜·직구 사각지대 논란, 강남 분유 신뢰 흔들",
      "link": "https://www.greened.kr/news/articleView.html?idxno=337045",
      "pub_date": "Sun, 15 Feb 2026 19:31:00 +0900",
      "signal": "strong",
      "trigger": "리콜"
    },
    {
      "title": "대구시약사회, 한약사·창고형 약국 규제 입법 촉구",
      "link": "https://www.yakup.com/news/index.html?mode=view&cat=17&nid=323975",
      "pub_date": "Tue, 03 Mar 2026 09:54:00 +0900",
      "signal": "normal",
      "trigger": "규제"
    },
    {
      "title": "성분명처방 공론화…건보 중심 약가개편 본격 논의",
      "link": "https://www.kpanews.co.kr/news/articleView.html?idxno=530157",
      "pub_date": "Tue, 03 Mar 2026 09:10:00 +0900",
      "signal": "normal",
      "trigger": "약가"
    },
    {
      "title": "웰리렉 급여 청원 재연장...국회 복지위 3월까지 심사",
      "link": "https://www.pharmnews.com/news/articleView.html?idxno=301255",
      "pub_date": "Tue, 03 Feb 2026 05:56:00 +0900",
      "signal": "normal",
      "trigger": "급여"
    },
    {
      "title": "암보다 무서운 약값에 눈물...조기 유방암 환우, 급여화 촉구",
      "link": "https://www.pharmnews.com/news/articleView.html?idxno=300727",
      "pub_date": "Wed, 07 Jan 2026 06:00:00 +0900",
      "signal": "normal",
      "trigger": "급여"
    }
  ],
  "youtube_trends": [
    {
      "title": "비타민을 떨어뜨린 식이 #924일 #486일",
      "channel": "도식2",
      "views": 114323,
      "published": "2026-03-08T00:21:38Z",
      "video_id": "IhUf8s2TYNQ",
      "query": "비타민"
    },
    {
      "title": "#깻잎과상극음식#비타민씨파괴음식#건강한음식 #꼬북등산tv #건강정보",
      "channel": "꼬북등산tv",
      "views": 78600,
      "published": "2026-03-07T12:30:07Z",
      "video_id": "2uOjGYP6f14",
      "query": "비타민"
    },
    {
      "title": "비타민 멤버들 달라도 너무 다른 일상 이거 맞아요?😂(밀착 카메라 🎥) #재밌는영상 #재밌는 #웃긴 #웃긴영상 #funny #예능 #브이로그 #일상 #일상브이로그",
      "channel": "Clevr TV [클레버티비]",
      "views": 77370,
      "published": "2026-03-07T08:00:16Z",
      "video_id": "F3dmMdydqi0",
      "query": "비타민"
    },
    {
      "title": "비만약 원가 7천원 살찐 사람 사라집니다 (정재훈 약사)",
      "channel": "언더스탠딩 : 세상의 모든 지식",
      "views": 53366,
      "published": "2026-03-07T05:55:00Z",
      "video_id": "YVRsiXHox1I",
      "query": "약사"
    },
    {
      "title": "\"아무 때나 먹으면 맹물입니다\" 의사가 정해준 영양제 복용 시간표",
      "channel": "백세인생창고",
      "views": 40700,
      "published": "2026-03-07T00:57:13Z",
      "video_id": "lcsyq-lxJbw",
      "query": "영양제"
    },
    {
      "title": "비타민C 먹고 동맥경화 검사를 받았다",
      "channel": "송학운",
      "views": 37905,
      "published": "2026-03-07T01:07:41Z",
      "video_id": "6EeRg2rDs5U",
      "query": "비타민"
    },
    {
      "title": "영양제에만 13억 쓰는 갑부가 추천하는 '영양제' 4가지  #시니어건강  #시니어정보",
      "channel": "장수레시피",
      "views": 31974,
      "published": "2026-03-07T09:45:03Z",
      "video_id": "frPZivxPykk",
      "query": "영양제"
    }
  ],
  "briefing": null
}