{
  "date": "2026-03-05",
  "updated_at": "2026-03-05 18:19",
  "naver_updated_at": "2026-03-05 18:19",
  "youtube_updated_at": "2026-03-05 15:41",
  "topics": [
    {
      "keyword": "치약",
      "score": 91.0,
      "verdict": "now",
      "n": 40,
      "t": 0,
      "w": 30,
      "r": 1.3,
      "change_rate": -6.7,
      "intent_type": "중립",
      "pharma_keywords": [
        "성분",
        "함량"
      ],
      "g_total": 3478912,
      "g_expert": 12499,
      "g_label": "전문가 갭 큼",
      "news_count": 28,
      "news_headlines": [
        {
          "title": "이채연 집 공개, 과시 민망하다면서 ‘명품 잔치’ [DA클립]",
          "link": "https://m.entertain.naver.com/article/382/0001259651"
        },
        {
          "title": "금지 성분 치약 판매…애경산업 수입업무정지 3개월",
          "link": "https://www.etoday.co.kr/news/view/2562417"
        }
      ],
      "ai_summary": "치약은 단순히 '많이 짜서 구석구석 닦으면' 효과가 좋다고 알려졌지만, 실제론 성분과 양, 접촉 시간이 훨씬 중요합니다.\n약사 관점: 불소·질산칼륨·초산아연 등 활성 성분의 농도와 pH, 마모도(RDA)가 치약 효능을 결정 → 성분표 해석과 개인 구강 상태별 맞춤 선택법으로 차별화 가능"
    },
    {
      "keyword": "정지",
      "score": 89.6,
      "verdict": "now",
      "n": 40,
      "t": 10,
      "w": 20,
      "r": 1.28,
      "change_rate": 11.6,
      "intent_type": "구매/추천형",
      "pharma_keywords": [
        "처방",
        "약물"
      ],
      "g_total": 4645955,
      "g_expert": 19070,
      "g_label": "전문가 갭 큼",
      "news_count": 27,
      "news_headlines": [
        {
          "title": "법원, 국민의힘 배현진 징계 효력정지 가처분 인용",
          "link": "https://www.goodmorningcc.com/news/articleView.html?idxno=442304"
        },
        {
          "title": "'피해자는 손흥민인데, 손흥민에게 억울함 호소' 당연한 결말…출전 정...",
          "link": "https://m.sports.naver.com/wfootball/article/411/0000078618"
        }
      ],
      "ai_summary": ""
    },
    {
      "keyword": "유플라이마",
      "score": 81.0,
      "verdict": "now",
      "n": 15,
      "t": 15,
      "w": 30,
      "r": 1.35,
      "change_rate": 19.2,
      "intent_type": "중립",
      "pharma_keywords": [
        "처방",
        "용량",
        "성분",
        "약물"
      ],
      "g_total": 5523,
      "g_expert": 104,
      "g_label": "전문가 갭 큼",
      "news_count": 30,
      "news_headlines": [
        {
          "title": "셀트리온, '유플라이마' 20mg 용량제형 식약처 국내 허가 획득",
          "link": "http://www.thefirstmedia.net/news/articleView.html?idxno=194827"
        },
        {
          "title": "셀트리온, ‘유플라이마’ 20mg 용량제형 국내 허가 획득",
          "link": "https://www.geconomy.co.kr/news/article.html?no=316817"
        }
      ],
      "aliases": [
        "유플라이마 베그젤마",
        "허쥬마 유플라이마",
        "유플라이마 등이",
        "램시마SC 유플라이마",
        "짐펜트라 유플라이마"
      ],
      "ai_summary": "생물의약품은 '용량만 늘리면' 효과가 비례적으로 증가한다고 생각하지만, 신약 허가는 약동학·약력학·안전성을 모두 재검증해야 합니다.\n약사/DDS 연구자 앵글: 20mg 신규 제형의 생동성 시험(BA/BE) 결과와 임상 데이터 → 단백질 의약품의 제형화 기술(주사제 안정성, 보관 조건)까지 풀면 전문성 강화"
    },
    {
      "keyword": "멜라닌 세포",
      "score": 75.0,
      "verdict": "now",
      "n": 30,
      "t": 25,
      "w": 5,
      "r": 1.25,
      "change_rate": 53.3,
      "intent_type": "중립",
      "pharma_keywords": [
        "성분"
      ],
      "g_total": 393112,
      "g_expert": 2815,
      "g_label": "전문가 갭 큼",
      "news_count": 3,
      "news_headlines": [
        {
          "title": "[브리프]아모레퍼시픽 LG생활건강 한국콜마 LF 무신사 外",
          "link": "http://www.biztribune.co.kr/news/articleView.html?idxno=349914"
        },
        {
          "title": "&quot;트럼프 목에 무슨 문제가?&quot; 의사들, '이 질환' 유력하다 주장",
          "link": "https://n.news.naver.com/mnews/article/296/0000098169?sid=103"
        }
      ],
      "ai_summary": "미백·색소 관련 화장품은 '피부 표면'에만 작용한다고 알려졌지만, 실제론 멜라닌 생성 과정의 여러 단계에서 작용하는 성분들이 다릅니다.\n약사 관점: 알파-알부틴(경쟁적 억제), 비타민C(항산화), 코직산(효소 억제) 등 메커니즘별 비교 → 의약외품 vs 화장품 분류 기준과 함께 효능 근거 설명"
    },
    {
      "keyword": "특별점검",
      "score": 72.8,
      "verdict": "now",
      "n": 40,
      "t": 0,
      "w": 30,
      "r": 1.04,
      "change_rate": 0,
      "intent_type": "구매/추천형",
      "pharma_keywords": [],
      "g_total": 2050471,
      "g_expert": 95744,
      "g_label": "전문가 부족",
      "news_count": 27,
      "news_headlines": [
        {
          "title": "정부, 첫 ‘석유 위기경보’ 발령…에너지 수급 긴장 고조",
          "link": "https://www.geconomy.co.kr/news/article.html?no=316846"
        },
        {
          "title": "해양환경공단, 포항지사 '현장 안전 관리 실태 점검·근로자 소통 간담...",
          "link": "https://www.cstimes.com/news/articleView.html?idxno=696111"
        }
      ],
      "ai_summary": ""
    },
    {
      "keyword": "발견",
      "score": 72.0,
      "verdict": "now",
      "n": 40,
      "t": 0,
      "w": 20,
      "r": 1.2,
      "change_rate": -6.0,
      "intent_type": "구매/추천형",
      "pharma_keywords": [
        "용량"
      ],
      "g_total": 48950045,
      "g_expert": 105008,
      "g_label": "전문가 갭 큼",
      "news_count": 27,
      "news_headlines": [
        {
          "title": "‘한국서 훼손 시신 발견’·‘서학개미 증세’ 등 가짜뉴스 유포자들 ...",
          "link": "https://m.entertain.naver.com/article/144/0001101635"
        },
        {
          "title": "인류는 왜 전쟁을 선택하는가",
          "link": "https://n.news.naver.com/mnews/article/005/0001835541?sid=103"
        }
      ],
      "ai_summary": ""
    },
    {
      "keyword": "칫솔 치약",
      "score": 67.5,
      "verdict": "hot",
      "n": 40,
      "t": 10,
      "w": 0,
      "r": 1.35,
      "change_rate": 13.8,
      "intent_type": "중립",
      "pharma_keywords": [
        "성분",
        "함량",
        "대사"
      ],
      "g_total": 2022787,
      "g_expert": 4244,
      "g_label": "전문가 갭 큼",
      "news_count": 0,
      "news_headlines": [
        {
          "title": "양치할 때 치약에 '물' 묻혀 말아?…의외로 의견 갈린다는 '이것' 알고 ...",
          "link": "https://www.wikitree.co.kr/articles/1122605"
        },
        {
          "title": "덴티스테, 새학기 맞아 올리브영 관악타운점 팝업 개장",
          "link": "https://www.m-i.kr/news/articleView.html?idxno=1342430"
        }
      ],
      "parent": "치약",
      "ai_summary": "치약을 물에 미리 적시거나 적시지 않는 것의 효과 차이는 '선호도'일 뿐 중요하지 않다고 생각하지만, 실제론 수분이 유효 성분의 용출과 농도에 영향을 줍니다.\n약사/DDS 앵글: 물의 첨가가 활성 성분의 생체이용률(용출 속도, 최고 농도)에 미치는 영향 → 습윤제, 연화제 같은 첨가제 역할과 과학적 양치법까지 설명 가능"
    },
    {
      "keyword": "로수젯",
      "score": 65.0,
      "verdict": "hot",
      "n": 30,
      "t": 0,
      "w": 20,
      "r": 1.3,
      "change_rate": -13.1,
      "intent_type": "의심/경고형",
      "pharma_keywords": [
        "처방",
        "용량",
        "성분",
        "부작용"
      ],
      "g_total": 2922,
      "g_expert": 190,
      "g_label": "전문가 부족",
      "news_count": 29,
      "news_headlines": [
        {
          "title": "대한약사회 &quot;한미약품 로수젯 원료 변경, 환자 안전 최우선 검토해야&quot;",
          "link": "https://www.hitnews.co.kr/news/articleView.html?idxno=74369"
        },
        {
          "title": "약사회 &quot;한미 '로수젯' 원료 변경, 환자 안전 최우선 검증돼야&quot;",
          "link": "https://www.yakup.com/news/index.html?mode=view&cat=17&nid=324159"
        }
      ],
      "aliases": [
        "치료제 '로수젯'",
        "한미약품 로수젯",
        "로수젯 아모잘탄",
        "로수젯정 부작용",
        "확인사항 로수젯정"
      ],
      "ai_summary": "원료 변경은 '같은 약이니까' 문제없다고 생각하지만, 제약학적으로 원료 공급처·정제 공정·불순물 프로필의 변화는 재평가 대상입니다.\n약사 앵글: 의약품 원료 변경 시 CMC(화학·제조·관리) 재검증, 생동성 시험 필요성 → 환자 안전과 약효 동등성 확보의 과학적 근거 설명"
    },
    {
      "keyword": "위고비 마운자",
      "score": 61.2,
      "verdict": "hot",
      "n": 40,
      "t": 5,
      "w": 0,
      "r": 1.36,
      "change_rate": 1.6,
      "intent_type": "의심/경고형",
      "pharma_keywords": [
        "처방",
        "용량",
        "성분",
        "부작용",
        "약물"
      ],
      "g_total": 867,
      "g_expert": 23,
      "g_label": "전문가 갭 큼",
      "news_count": 0,
      "news_headlines": [
        {
          "title": "위고비 끊자 뇌가 복수했다…15kg 뺀 여자의 처참한 결말",
          "link": "https://n.news.naver.com/mnews/article/025/0003504281?sid=103"
        },
        {
          "title": "‘두달 만에 14kg 감량’ 케이윌 “위고비 실패, ‘이것’ 효과 봤다”...",
          "link": "https://n.news.naver.com/mnews/article/296/0000097815?sid=103"
        }
      ],
      "parent": "마운자",
      "aliases": [
        "마운자",
        "위고비 마운자로",
        "위고비"
      ],
      "ai_summary": "GLP-1 수용체 작동제는 '복용만 중단하면' 다시 원래 몸무게로 돌아간다고 알려졌지만, 실제론 약물 중단 후 신경전달물질 회복 시간, 신진대사 적응 과정이 개인차가 큽니다.\n약사/DDS 연구자 앵글: 반감기(세마글루타이드 약 7일), 수용체 downregulation 회복 기간, 식욕 신호전달 복구 메커니즘 → 약물 회임(rebound) 현상의 과학적 설명과 의존성 예방 상담"
    },
    {
      "keyword": "치료제",
      "score": 57.1,
      "verdict": "hot",
      "n": 5,
      "t": 10,
      "w": 30,
      "r": 1.27,
      "change_rate": 6.0,
      "intent_type": "의심/경고형",
      "pharma_keywords": [
        "처방",
        "성분",
        "함량",
        "부작용",
        "약물"
      ],
      "g_total": 2074771,
      "g_expert": 71303,
      "g_label": "전문가 부족",
      "news_count": 37,
      "news_headlines": [
        {
          "title": "“내가 암 환자가 되던 날, 비로소 진짜 의사가 됐습니다”",
          "link": "https://n.news.naver.com/mnews/article/005/0001835542?sid=102"
        },
        {
          "title": "“한 번만 넣으면 스스로 치료한다”… 피츠버그대, ‘살아있는 안약’...",
          "link": "https://n.news.naver.com/mnews/article/023/0003962805?sid=105"
        }
      ],
      "aliases": [
        "치매 치료제",
        "치료제 개발",
        "치료제 만들기",
        "질환 치료제",
        "비듬 치료제",
        "비만치료제"
      ],
      "ai_summary": "치료제의 혁신은 '새로운 약물'의 등장으로만 평가되지만, 실제론 제형 기술(DDS)과 전달 경로의 개선이 효능과 부작용을 크게 결정합니다.\n약사/DDS 연구자 앵글: 약물 전달 시스템(리포솜, 나노입자, 점안제, 젤 기반 제형)의 생체 이용률 개선 사례 → DDS 관점에서 '같은 약, 다른 효과'의 실제 메커니즘 강조"
    },
    {
      "keyword": "약사회",
      "score": 54.6,
      "verdict": "hot",
      "n": 30,
      "t": 0,
      "w": 30,
      "r": 0.91,
      "change_rate": -19.9,
      "intent_type": "의심/경고형",
      "pharma_keywords": [
        "처방",
        "복용법",
        "용량",
        "성분",
        "부작용",
        "대사",
        "약물"
      ],
      "g_total": 60840,
      "g_expert": 31655,
      "g_label": "전문가 포화",
      "news_count": 29,
      "news_headlines": [
        {
          "title": "대한약사회 &quot;한미약품 로수젯 원료 변경, 환자 안전 최우선 검토해야&quot;",
          "link": "https://www.hitnews.co.kr/news/articleView.html?idxno=74369"
        },
        {
          "title": "강남구약사회, 청각장애 어르신 행사서 영양제 후원",
          "link": "https://www.yakup.com/news/index.html?mode=view&cat=17&nid=324161"
        }
      ],
      "aliases": [
        "지역 약사회",
        "4일 아산시약사회(회장",
        "한국병원약사회 빌딩",
        "서초동 한국병원약사회",
        "아산시약사회(회장 조성도)로"
      ],
      "ai_summary": ""
    },
    {
      "keyword": "상담하 특별",
      "score": 54.0,
      "verdict": "hot",
      "n": 40,
      "t": 0,
      "w": 0,
      "r": 1.35,
      "change_rate": 0,
      "intent_type": "중립",
      "pharma_keywords": [
        "처방",
        "복용법",
        "부작용",
        "약물"
      ],
      "g_total": 1100,
      "g_expert": 15,
      "g_label": "전문가 갭 큼",
      "news_count": 0,
      "news_headlines": [
        {
          "title": "넘어졌다, 허리 욱신거리긴 하는데… 병원 꼭 가야 할까?",
          "link": "https://n.news.naver.com/mnews/article/346/0000102018?sid=103"
        },
        {
          "title": "토트넘, 쿨루셉스키 부상 결장... '17년 무관 탈출'+'손흥민 첫 트로피'...",
          "link": "https://www.ggilbo.com/news/articleView.html?idxno=1090138"
        }
      ],
      "parent": "특별점검",
      "ai_summary": ""
    },
    {
      "keyword": "가능성 발견",
      "score": 53.6,
      "verdict": "hot",
      "n": 40,
      "t": 0,
      "w": 0,
      "r": 1.34,
      "change_rate": 0,
      "intent_type": "의심/경고형",
      "pharma_keywords": [
        "부작용",
        "대사"
      ],
      "g_total": 5233684,
      "g_expert": 19745,
      "g_label": "전문가 갭 큼",
      "news_count": 0,
      "news_headlines": [
        {
          "title": "“잔해에 깔린 하메네이 시신” 이 와중에 가짜…AI가 만든 시신 vs AI가...",
          "link": "https://n.news.naver.com/mnews/article/011/0004596287?sid=104"
        },
        {
          "title": "카르다노, 고래들 2억 3,000만 개 대이동...분석가 &quot;지지선 못 지키면 급...",
          "link": "http://coinreaders.com/221526"
        }
      ],
      "parent": "발견",
      "ai_summary": ""
    },
    {
      "keyword": "치약 선택",
      "score": 52.8,
      "verdict": "hot",
      "n": 40,
      "t": 0,
      "w": 0,
      "r": 1.32,
      "change_rate": 0,
      "intent_type": "구매/추천형",
      "pharma_keywords": [
        "용량",
        "성분",
        "함량",
        "대사"
      ],
      "g_total": 1074264,
      "g_expert": 4129,
      "g_label": "전문가 갭 큼",
      "news_count": 0,
      "news_headlines": [
        {
          "title": "양치할 때 치약에 '물' 묻혀 말아?…의외로 의견 갈린다는 '이것' 알고 ...",
          "link": "https://www.wikitree.co.kr/articles/1122605"
        },
        {
          "title": "[브리프]신세계 롯데마트 다이소몰 CJ온스타일 GS리테일 롯데월드 外",
          "link": "http://www.biztribune.co.kr/news/articleView.html?idxno=349741"
        }
      ],
      "parent": "치약",
      "ai_summary": "좋은 치약 선택은 '유명 브랜드' 또는 '가격이 비싼 것'이 기준이라고 생각하지만, 실제론 구강 상태(산성, 민감성, 충치 위험도)에 맞는 성분 구성이 답입니다.\n약사 앵gl: 불소 농도(950~1500ppm), RDA(마모도), pH, 특수 첨가제(칼슘, 질산칼륨, 초산아연)의 개인맞춤 추천 → 성분표 읽기로 과학적 선택 가이드 제공"
    },
    {
      "keyword": "불소 치약",
      "score": 52.8,
      "verdict": "hot",
      "n": 40,
      "t": 0,
      "w": 0,
      "r": 1.32,
      "change_rate": -16.1,
      "intent_type": "구매/추천형",
      "pharma_keywords": [
        "성분",
        "함량",
        "약물"
      ],
      "g_total": 554022,
      "g_expert": 1920,
      "g_label": "전문가 갭 큼",
      "news_count": 0,
      "news_headlines": [
        {
          "title": "양치할 때 치약에 '물' 묻혀 말아?…의외로 의견 갈린다는 '이것' 알고 ...",
          "link": "https://www.wikitree.co.kr/articles/1122605"
        },
        {
          "title": "[유통 소식] 파리바게뜨, 990원 '한입 브레드' 선보인다 外",
          "link": "http://www.dailypop.kr/news/articleView.html?idxno=96941"
        }
      ],
      "parent": "치약",
      "aliases": [
        "치약 불소"
      ],
      "ai_summary": "불소는 '독성'이 있으니 적게 함유된 제품이 안전하다고 알려졌지만, 실제론 치아 건강을 위한 적정 농도(950~1500ppm)와 전신 흡수 정도는 완전히 다릅니다.\n약사/DDS 앵글: 불소의 생체 이용률, 신장 배출 속도, 연령대별 권장량 → 불소 이온의 에나멜질 침투 메커니즘과 과불소증 예방 용량 설명으로 신뢰도 확보"
    },
    {
      "keyword": "마운자로 처방",
      "score": 50.4,
      "verdict": "hot",
      "n": 40,
      "t": 0,
      "w": 0,
      "r": 1.26,
      "change_rate": -29.0,
      "intent_type": "의심/경고형",
      "pharma_keywords": [
        "처방",
        "용량",
        "성분",
        "부작용",
        "대사",
        "약물"
      ],
      "g_total": 21105,
      "g_expert": 1006,
      "g_label": "전문가 부족",
      "news_count": 0,
      "news_headlines": [
        {
          "title": "식약처, 3월 5일부터 비만치료제 표방 식품 특별점검",
          "link": "https://medicalworldnews.co.kr/news/view.php?idx=1510973360"
        },
        {
          "title": "식약처, '위고비·마운자로' 표방 식품 집중 점검",
          "link": "https://www.ktv.go.kr/content/view?content_id=749387"
        }
      ],
      "parent": "마운자",
      "aliases": [
        "마운자로"
      ],
      "ai_summary": ""
    },
    {
      "keyword": "조기 발견",
      "score": 50.0,
      "verdict": "hot",
      "n": 40,
      "t": 0,
      "w": 0,
      "r": 1.25,
      "change_rate": 0,
      "intent_type": "중립",
      "pharma_keywords": [
        "용량"
      ],
      "g_total": 3805757,
      "g_expert": 10797,
      "g_label": "전문가 갭 큼",
      "news_count": 0,
      "news_headlines": [
        {
          "title": "최대호표 복지안전망...안양시 드림스타트 413가구 발굴 추진",
          "link": "http://www.fieldnews.kr/news/articleView.html?idxno=26772"
        },
        {
          "title": "인천시, '과수 구제역' 화상병 차단 총력…사과·배 농가 의무교육 실시",
          "link": "https://www.cstimes.com/news/articleView.html?idxno=696136"
        }
      ],
      "parent": "발견",
      "ai_summary": ""
    },
    {
      "keyword": "발견 즉시",
      "score": 50.0,
      "verdict": "hot",
      "n": 40,
      "t": 0,
      "w": 0,
      "r": 1.25,
      "change_rate": 0,
      "intent_type": "중립",
      "pharma_keywords": [
        "용량"
      ],
      "g_total": 2608111,
      "g_expert": 9808,
      "g_label": "전문가 갭 큼",
      "news_count": 0,
      "news_headlines": [
        {
          "title": "인천시, '과수 구제역' 화상병 차단 총력…사과·배 농가 의무교육 실시",
          "link": "https://www.cstimes.com/news/articleView.html?idxno=696136"
        },
        {
          "title": "오늘의 운세 띠별 운세 3월6일",
          "link": "https://www.bntnews.co.kr/article/view/bnt202603060001"
        }
      ],
      "parent": "발견",
      "ai_summary": ""
    },
    {
      "keyword": "치약짜개) 치약",
      "score": 49.2,
      "verdict": "hot",
      "n": 40,
      "t": 0,
      "w": 0,
      "r": 1.23,
      "change_rate": 0,
      "intent_type": "구매/추천형",
      "pharma_keywords": [
        "용량",
        "성분"
      ],
      "g_total": 11281,
      "g_expert": 16,
      "g_label": "전문가 갭 큼",
      "news_count": 0,
      "news_headlines": [
        {
          "title": "사연 있는 중고 물품…자원 순환·추억 소환 ‘돌고 도네’",
          "link": "http://www.kwangju.co.kr/article.php?aid=1770809400795618006"
        },
        {
          "title": "“다 쓴 치약 ‘이렇게’ 써보세요”… 집안 곰팡이 싹 사라진다고?",
          "link": "https://n.news.naver.com/mnews/article/296/0000097368?sid=103"
        }
      ],
      "parent": "치약",
      "ai_summary": ""
    },
    {
      "keyword": "마운자로 5주차",
      "score": 49.2,
      "verdict": "hot",
      "n": 40,
      "t": 0,
      "w": 0,
      "r": 1.23,
      "change_rate": 0,
      "intent_type": "구매/추천형",
      "pharma_keywords": [
        "처방",
        "용량",
        "성분",
        "부작용",
        "대사",
        "약물"
      ],
      "g_total": 793,
      "g_expert": 31,
      "g_label": "전문가 부족",
      "news_count": 0,
      "news_headlines": [
        {
          "title": "마운자로 품귀에 ‘부르는 게 값’… 약국별 최대 18만원 차",
          "link": "https://n.news.naver.com/mnews/article/014/0005484553?sid=103"
        },
        {
          "title": "마운자로 광풍에 부르는게 값? 최대 18만원까지 차이",
          "link": "https://n.news.naver.com/mnews/article/014/0005484451?sid=103"
        }
      ],
      "parent": "마운자",
      "ai_summary": ""
    },
    {
      "keyword": "해방촌 마운자로",
      "score": 49.2,
      "verdict": "hot",
      "n": 40,
      "t": 0,
      "w": 0,
      "r": 1.23,
      "change_rate": 0,
      "intent_type": "의심/경고형",
      "pharma_keywords": [
        "처방"
      ],
      "g_total": 14,
      "g_expert": 0,
      "g_label": "전문가 부족",
      "news_count": 0,
      "news_headlines": [],
      "parent": "마운자",
      "ai_summary": ""
    },
    {
      "keyword": "정지 기능이",
      "score": 48.8,
      "verdict": "hot",
      "n": 40,
      "t": 0,
      "w": 0,
      "r": 1.22,
      "change_rate": 0,
      "intent_type": "구매/추천형",
      "pharma_keywords": [
        "용량"
      ],
      "g_total": 864223,
      "g_expert": 4344,
      "g_label": "전문가 갭 큼",
      "news_count": 0,
      "news_headlines": [
        {
          "title": "고려아연, 정기주총 앞두고 주주서한 발송 .... &quot;美프로젝트 성공 위해...",
          "link": "http://www.worktoday.co.kr/news/articleView.html?idxno=82081"
        },
        {
          "title": "최혁진 의원 “원주시 주민자치 관련 ‘행안부 입장 왜곡’ 확인”",
          "link": "https://www.kukinews.com/article/view/kuk202603050265"
        }
      ],
      "parent": "정지",
      "ai_summary": ""
    },
    {
      "keyword": "자동 정지",
      "score": 48.4,
      "verdict": "hot",
      "n": 40,
      "t": 0,
      "w": 0,
      "r": 1.21,
      "change_rate": 0,
      "intent_type": "구매/추천형",
      "pharma_keywords": [
        "용량"
      ],
      "g_total": 552351,
      "g_expert": 1469,
      "g_label": "전문가 갭 큼",
      "news_count": 0,
      "news_headlines": [
        {
          "title": "돈치치, 목숨 하나 남았다…갈 길 바쁜 레이커스 또 골머리! 할렐루카 ...",
          "link": "https://m.sports.naver.com/basketball/article/139/0002243314"
        },
        {
          "title": "[이준섭의 시선N] '외국인 관광객 3000만' 목표…숫자 늘리기보다 관광...",
          "link": "https://www.nc.press/news/articleView.html?idxno=609365"
        }
      ],
      "parent": "정지",
      "ai_summary": ""
    },
    {
      "keyword": "임신 기간",
      "score": 48.3,
      "verdict": "hot",
      "n": 30,
      "t": 0,
      "w": 5,
      "r": 1.38,
      "change_rate": -6.2,
      "intent_type": "의심/경고형",
      "pharma_keywords": [
        "처방",
        "용량",
        "부작용",
        "약물"
      ],
      "g_total": 1783034,
      "g_expert": 23982,
      "g_label": "전문가 갭 큼",
      "news_count": 3,
      "news_headlines": [
        {
          "title": "두 발로 서는 게레눅",
          "link": "http://www.gjdream.com/news/articleView.html?idxno=667635"
        },
        {
          "title": "“유방도 생리를 한다”던데… 무슨 말인지 봤더니?",
          "link": "https://n.news.naver.com/mnews/article/346/0000105740?sid=103"
        }
      ],
      "ai_summary": ""
    },
    {
      "keyword": "면역 세포",
      "score": 48.3,
      "verdict": "hot",
      "n": 30,
      "t": 0,
      "w": 5,
      "r": 1.38,
      "change_rate": 0.0,
      "intent_type": "의심/경고형",
      "pharma_keywords": [
        "상호작용",
        "성분",
        "부작용",
        "대사"
      ],
      "g_total": 2712730,
      "g_expert": 48193,
      "g_label": "전문가 갭 큼",
      "news_count": 3,
      "news_headlines": [
        {
          "title": "[200자 읽기] ‘시한부’에서 살아남은 사람들",
          "link": "https://n.news.naver.com/mnews/article/005/0001835535?sid=103"
        },
        {
          "title": "[TV조선] 변비를 이겨내는 비법",
          "link": "https://n.news.naver.com/mnews/article/023/0003962752?sid=103"
        }
      ],
      "ai_summary": ""
    },
    {
      "keyword": "세포",
      "score": 48.0,
      "verdict": "hot",
      "n": 5,
      "t": 15,
      "w": 20,
      "r": 1.2,
      "change_rate": 18.2,
      "intent_type": "구매/추천형",
      "pharma_keywords": [
        "처방",
        "성분",
        "대사"
      ],
      "g_total": 10409504,
      "g_expert": 123309,
      "g_label": "전문가 갭 큼",
      "news_count": 33,
      "news_headlines": [
        {
          "title": "[200자 읽기] ‘시한부’에서 살아남은 사람들",
          "link": "https://n.news.naver.com/mnews/article/005/0001835535?sid=103"
        },
        {
          "title": "“한 번만 넣으면 스스로 치료한다”… 피츠버그대, ‘살아있는 안약’...",
          "link": "https://n.news.naver.com/mnews/article/023/0003962805?sid=105"
        }
      ],
      "ai_summary": ""
    },
    {
      "keyword": "발견 티타늄",
      "score": 48.0,
      "verdict": "hot",
      "n": 40,
      "t": 0,
      "w": 0,
      "r": 1.2,
      "change_rate": 0,
      "intent_type": "구매/추천형",
      "pharma_keywords": [
        "성분"
      ],
      "g_total": 54775,
      "g_expert": 209,
      "g_label": "전문가 갭 큼",
      "news_count": 0,
      "news_headlines": [
        {
          "title": "[인터뷰] 황재원 골프아카데미 원장, “베르쿠치(Bercucci) 드라이버를 ...",
          "link": "https://www.geconomy.co.kr/news/article.html?no=316590"
        },
        {
          "title": "비파열성 뇌동맥류 “크기 작고 파열 위험 낮다면 변화 관찰하며 꾸준히...",
          "link": "https://n.news.naver.com/mnews/article/082/0001368964?sid=103"
        }
      ],
      "parent": "발견",
      "ai_summary": ""
    },
    {
      "keyword": "일시 정지",
      "score": 47.2,
      "verdict": "hot",
      "n": 40,
      "t": 0,
      "w": 0,
      "r": 1.18,
      "change_rate": -27.4,
      "intent_type": "구매/추천형",
      "pharma_keywords": [],
      "g_total": 417210,
      "g_expert": 1598,
      "g_label": "전문가 갭 큼",
      "news_count": 0,
      "news_headlines": [
        {
          "title": "최대 낙폭 다음날 최대 상승 코스피…단숨에 5583 회복",
          "link": "https://n.news.naver.com/mnews/article/025/0003507201?sid=101"
        },
        {
          "title": "'역대 최대 상승' 중동 전쟁에 널뛰는 코스피",
          "link": "https://n.news.naver.com/mnews/article/087/0001178117?sid=101"
        }
      ],
      "parent": "정지",
      "ai_summary": ""
    },
    {
      "keyword": "드디어 발견",
      "score": 47.2,
      "verdict": "hot",
      "n": 40,
      "t": 0,
      "w": 0,
      "r": 1.18,
      "change_rate": 0,
      "intent_type": "구매/추천형",
      "pharma_keywords": [
        "용량"
      ],
      "g_total": 3663478,
      "g_expert": 10180,
      "g_label": "전문가 갭 큼",
      "news_count": 0,
      "news_headlines": [
        {
          "title": "오늘의 운세 띠별 운세 3월6일",
          "link": "https://www.bntnews.co.kr/article/view/bnt202603060001"
        },
        {
          "title": "국화, 최종 선택 포기…28기 영수♥튤립·22기 상철♥백합 최종 커플 ('...",
          "link": "https://m.entertain.naver.com/article/213/0001376294"
        }
      ],
      "parent": "발견",
      "ai_summary": ""
    },
    {
      "keyword": "건강 지키",
      "score": 43.8,
      "verdict": "warm",
      "n": 30,
      "t": 0,
      "w": 5,
      "r": 1.25,
      "change_rate": 0,
      "intent_type": "중립",
      "pharma_keywords": [
        "부작용"
      ],
      "g_total": 15513,
      "g_expert": 172,
      "g_label": "전문가 갭 큼",
      "news_count": 3,
      "news_headlines": [
        {
          "title": "서울시간호사회, 17일 '제79회 정기 대의원총회' 연다",
          "link": "https://www.medipana.com/news/articleView.html?idxno=407774"
        },
        {
          "title": "부산시약사회 &quot;정부는 약사·한약사간 면허범위 바로 세워야&quot;",
          "link": "http://www.bokuennews.com/news/article.html?no=274122"
        }
      ],
      "ai_summary": ""
    },
    {
      "keyword": "약국",
      "score": 42.8,
      "verdict": "warm",
      "n": 0,
      "t": 10,
      "w": 30,
      "r": 1.07,
      "change_rate": 8.5,
      "intent_type": "구매/추천형",
      "pharma_keywords": [
        "처방",
        "성분"
      ],
      "g_total": 3654613,
      "g_expert": 458631,
      "g_label": "보통",
      "news_count": 35,
      "news_headlines": [
        {
          "title": "대구시 달서구 바른연합소아청소년과의원, 달빛어린이병원 신규 지정",
          "link": "https://tk.newdaily.co.kr/site/data/html/2026/03/05/2026030500486.html"
        },
        {
          "title": "이 대통령 &quot;사무장병원 근절하라&quot;...공단 특사경 도입 주문",
          "link": "https://www.dailypharm.com/user/news/336242?REFERER=NP"
        }
      ],
      "ai_summary": ""
    },
    {
      "keyword": "오쿠 건강드림",
      "score": 42.4,
      "verdict": "warm",
      "n": 30,
      "t": 0,
      "w": 5,
      "r": 1.21,
      "change_rate": 0,
      "intent_type": "구매/추천형",
      "pharma_keywords": [
        "용량"
      ],
      "g_total": 500,
      "g_expert": 1,
      "g_label": "전문가 갭 큼",
      "news_count": 3,
      "news_headlines": [
        {
          "title": "쿠팡, 와우회원 대상 여름맞이 '쿨 서머 세일' 진행…최대 50% ↓",
          "link": "http://www.newsdream.kr/news/articleView.html?idxno=85909"
        },
        {
          "title": "화면해설방송 편성안내(4월 13일~4월 19일)",
          "link": "http://beminor.com/detail.php?number=14563&thread=04r09"
        }
      ],
      "ai_summary": ""
    },
    {
      "keyword": "영양제",
      "score": 42.0,
      "verdict": "warm",
      "n": 15,
      "t": 0,
      "w": 20,
      "r": 1.2,
      "change_rate": -5.1,
      "intent_type": "구매/추천형",
      "pharma_keywords": [
        "처방",
        "성분",
        "함량",
        "부작용"
      ],
      "g_total": 4821163,
      "g_expert": 190862,
      "g_label": "전문가 부족",
      "news_count": 28,
      "news_headlines": [
        {
          "title": "이채연 집 공개, 과시 민망하다면서 ‘명품 잔치’ [DA클립]",
          "link": "https://m.entertain.naver.com/article/382/0001259651"
        },
        {
          "title": "“한 번만 넣으면 스스로 치료한다”… 피츠버그대, ‘살아있는 안약’...",
          "link": "https://n.news.naver.com/mnews/article/023/0003962805?sid=105"
        }
      ],
      "ai_summary": ""
    },
    {
      "keyword": "집중",
      "score": 41.3,
      "verdict": "warm",
      "n": 5,
      "t": 0,
      "w": 30,
      "r": 1.18,
      "change_rate": -0.5,
      "intent_type": "구매/추천형",
      "pharma_keywords": [
        "성분"
      ],
      "g_total": 42567584,
      "g_expert": 88304,
      "g_label": "전문가 갭 큼",
      "news_count": 30,
      "news_headlines": [
        {
          "title": "안양시, 아크로베스티뉴 청년임대주택 ‘인기’",
          "link": "https://n.news.naver.com/mnews/article/468/0001222222?sid=102"
        },
        {
          "title": "[동그라미 만평] 검찰 무오류 &quot;관봉권 띠지 폐기&quot; 혐의없음.",
          "link": "https://www.goodmorningcc.com/news/articleView.html?idxno=442303"
        }
      ],
      "ai_summary": ""
    },
    {
      "keyword": "건강드림 글라스",
      "score": 40.2,
      "verdict": "warm",
      "n": 30,
      "t": 0,
      "w": 5,
      "r": 1.15,
      "change_rate": 0,
      "intent_type": "구매/추천형",
      "pharma_keywords": [
        "용량"
      ],
      "g_total": 129,
      "g_expert": 1,
      "g_label": "전문가 갭 큼",
      "news_count": 3,
      "news_headlines": [
        {
          "title": "무안군, 눈 건강지킴이 안경 지원 추진",
          "link": "https://n.news.naver.com/mnews/article/031/0001010308?sid=102"
        },
        {
          "title": "무안군 드림스타트, '안경 구입비 지원'",
          "link": "http://www.newsmaker.or.kr/news/articleView.html?idxno=174800"
        }
      ],
      "ai_summary": ""
    },
    {
      "keyword": "척추 건강",
      "score": 39.2,
      "verdict": "warm",
      "n": 30,
      "t": 0,
      "w": 5,
      "r": 1.12,
      "change_rate": 0,
      "intent_type": "구매/추천형",
      "pharma_keywords": [],
      "g_total": 2638810,
      "g_expert": 7095,
      "g_label": "전문가 갭 큼",
      "news_count": 3,
      "news_headlines": [
        {
          "title": "남지현, ‘힙업 비결’ 공개… “특히 ‘이 운동’이 효과 좋아”",
          "link": "https://n.news.naver.com/mnews/article/346/0000105744?sid=103"
        },
        {
          "title": "울산엘리야병원, 호계공설시장 상인회와 '맞춤형 의료지원' 맞손",
          "link": "https://www.cstimes.com/news/articleView.html?idxno=696099"
        }
      ],
      "ai_summary": ""
    },
    {
      "keyword": "표방 식품",
      "score": 38.1,
      "verdict": "warm",
      "n": 15,
      "t": 0,
      "w": 15,
      "r": 1.27,
      "change_rate": 0,
      "intent_type": "의심/경고형",
      "pharma_keywords": [
        "처방",
        "복용법",
        "성분",
        "함량",
        "부작용"
      ],
      "g_total": 25971,
      "g_expert": 1111,
      "g_label": "전문가 부족",
      "news_count": 3,
      "news_headlines": [
        {
          "title": "식약처, 3월 5일부터 비만치료제 표방 식품 특별점검",
          "link": "https://medicalworldnews.co.kr/news/view.php?idx=1510973360"
        },
        {
          "title": "“팔레스타인 파괴 관여한 기업 참여 취업박람회 거부”",
          "link": "https://n.news.naver.com/mnews/article/032/0003431531?sid=102"
        }
      ],
      "ai_summary": ""
    },
    {
      "keyword": "식약처",
      "score": 37.5,
      "verdict": "warm",
      "n": 0,
      "t": 0,
      "w": 30,
      "r": 1.25,
      "change_rate": -16.1,
      "intent_type": "중립",
      "pharma_keywords": [
        "처방",
        "상호작용",
        "성분",
        "함량",
        "부작용",
        "대사",
        "약물"
      ],
      "g_total": 1862323,
      "g_expert": 66696,
      "g_label": "전문가 부족",
      "news_count": 97,
      "news_headlines": [
        {
          "title": "식약처-지방정부, 의료기관 프로포폴 취급 적정성 특별점검",
          "link": "https://medicalworldnews.co.kr/news/view.php?idx=1510973355"
        },
        {
          "title": "식약처, 3월 5일부터 비만치료제 표방 식품 특별점검",
          "link": "https://medicalworldnews.co.kr/news/view.php?idx=1510973360"
        }
      ],
      "ai_summary": ""
    },
    {
      "keyword": "담석증",
      "score": 36.0,
      "verdict": "warm",
      "n": 5,
      "t": 0,
      "w": 20,
      "r": 1.44,
      "change_rate": -12.9,
      "intent_type": "의심/경고형",
      "pharma_keywords": [
        "처방",
        "성분",
        "부작용",
        "대사"
      ],
      "g_total": 89538,
      "g_expert": 1687,
      "g_label": "전문가 갭 큼",
      "news_count": 34,
      "news_headlines": [
        {
          "title": "눈 퉁퉁 부은 이혜영, 폐암·담석증 이어 림프 부종도 겪었다…&quot;건강 회...",
          "link": "https://m.entertain.naver.com/article/312/0000750357"
        },
        {
          "title": "'다이어트 주사제' 열풍 속 담석증 주의보… 10년 새 환자 2배 급증",
          "link": "http://www.bokuennews.com/news/article.html?no=274682"
        }
      ],
      "ai_summary": ""
    },
    {
      "keyword": "전동킥보드음주운전 면허정지취소",
      "score": 34.0,
      "verdict": "warm",
      "n": 40,
      "t": 0,
      "w": 0,
      "r": 0.85,
      "change_rate": 0,
      "intent_type": "의심/경고형",
      "pharma_keywords": [],
      "g_total": 19043,
      "g_expert": 19369,
      "g_label": "전문가 포화",
      "news_count": 0,
      "news_headlines": [
        {
          "title": "학교 앞 음주운전 단속… &quot;내리세요, 면허취소&quot;",
          "link": "https://n.news.naver.com/mnews/article/014/0005486308?sid=102"
        },
        {
          "title": "[르포] 등굣길 음주운전 &quot;꼼짝마&quot; 경찰 '속시원한 교통단속'",
          "link": "https://n.news.naver.com/mnews/article/014/0005486009?sid=102"
        }
      ],
      "parent": "정지",
      "ai_summary": ""
    },
    {
      "keyword": "면허정지취소 상담비용수임료선임",
      "score": 34.0,
      "verdict": "warm",
      "n": 40,
      "t": 0,
      "w": 0,
      "r": 0.85,
      "change_rate": 0,
      "intent_type": "의심/경고형",
      "pharma_keywords": [],
      "g_total": 151050,
      "g_expert": 153576,
      "g_label": "전문가 포화",
      "news_count": 0,
      "news_headlines": [
        {
          "title": "음주운전 초범이라도 초기부터 전문가와 대응해야",
          "link": "https://www.ksilbo.co.kr/news/articleView.html?idxno=999711"
        },
        {
          "title": "박민정 변호사, 전문성·정의에 대한 신념으로 변호한다 [쿠키인터뷰]",
          "link": "http://www.kukinews.com/newsView/kuk202111220009"
        }
      ],
      "parent": "정지",
      "ai_summary": ""
    },
    {
      "keyword": "성지 약국",
      "score": 32.7,
      "verdict": "warm",
      "n": 15,
      "t": 10,
      "w": 5,
      "r": 1.09,
      "change_rate": 11.3,
      "intent_type": "구매/추천형",
      "pharma_keywords": [
        "처방",
        "용량",
        "부작용"
      ],
      "g_total": 26557,
      "g_expert": 5395,
      "g_label": "보통",
      "news_count": 3,
      "news_headlines": [
        {
          "title": "&quot;원주 인재양성 든든한 버팀목&quot; 촛불장학회 36년째 후원 귀감",
          "link": "https://n.news.naver.com/mnews/article/654/0000169178?sid=102"
        },
        {
          "title": "제60회 납세자의 날 모범납세자 포상명단",
          "link": "http://www.intn.co.kr/news/articleView.html?idxno=2049324"
        }
      ],
      "ai_summary": ""
    },
    {
      "keyword": "비만약",
      "score": 27.6,
      "verdict": "warm",
      "n": 0,
      "t": 0,
      "w": 20,
      "r": 1.38,
      "change_rate": -28.4,
      "intent_type": "의심/경고형",
      "pharma_keywords": [
        "처방",
        "금기",
        "성분",
        "부작용",
        "대사",
        "약물"
      ],
      "g_total": 47588,
      "g_expert": 1180,
      "g_label": "전문가 갭 큼",
      "news_count": 44,
      "news_headlines": [
        {
          "title": "[분석] 삼천당제약 주가 '껑충'… 업계 잭팟은 '비만약?'",
          "link": "http://www.economytalk.kr/news/articleView.html?idxno=418622"
        },
        {
          "title": "위고비 특허 만료 스타트, 올해 복제약 잇따른다",
          "link": "https://n.news.naver.com/mnews/article/296/0000098212?sid=101"
        }
      ],
      "ai_summary": ""
    },
    {
      "keyword": "다이어트",
      "score": 25.4,
      "verdict": "warm",
      "n": 0,
      "t": 0,
      "w": 20,
      "r": 1.27,
      "change_rate": -15.5,
      "intent_type": "구매/추천형",
      "pharma_keywords": [
        "금기",
        "함량",
        "대사"
      ],
      "g_total": 20888287,
      "g_expert": 69816,
      "g_label": "전문가 갭 큼",
      "news_count": 53,
      "news_headlines": [
        {
          "title": "“얼굴 살 점점 빠지고 있다” 랄랄, 다이어트 음식 공개… 뭘까?",
          "link": "https://n.news.naver.com/mnews/article/346/0000105745?sid=004"
        },
        {
          "title": "이채연 집 공개, 과시 민망하다면서 ‘명품 잔치’ [DA클립]",
          "link": "https://m.entertain.naver.com/article/382/0001259651"
        }
      ],
      "ai_summary": ""
    },
    {
      "keyword": "공공심야약국",
      "score": 19.2,
      "verdict": "pass",
      "n": 5,
      "t": 0,
      "w": 20,
      "r": 0.77,
      "change_rate": -4.7,
      "intent_type": "구매/추천형",
      "pharma_keywords": [
        "처방",
        "대사"
      ],
      "g_total": 13137,
      "g_expert": 4393,
      "g_label": "전문가 포화",
      "news_count": 30,
      "news_headlines": [
        {
          "title": "의성군보건소, 공공 심야 약국 지속 운영",
          "link": "https://www.ksmnews.co.kr/news/view.php?idx=593224"
        },
        {
          "title": "문경시, 올해 공공심야약국 4개소 가동",
          "link": "http://www.hidomin.com/news/articleView.html?idxno=611203"
        }
      ],
      "ai_summary": ""
    }
  ],
  "pharma_news": [
    {
      "title": "셀트리온, '유플라이마' 20mg 용량제형 식약처 국내 허가 획득",
      "link": "http://www.thefirstmedia.net/news/articleView.html?idxno=194827",
      "pub_date": "Thu, 05 Mar 2026 21:22:00 +0900",
      "signal": "strong",
      "trigger": "허가"
    },
    {
      "title": "식약처, '위고비·마운자로' 표방 식품 특별점검…온라인 부당광고 집중...",
      "link": "https://www.ccdn.co.kr/news/articleView.html?idxno=1066210",
      "pub_date": "Thu, 05 Mar 2026 18:54:00 +0900",
      "signal": "global",
      "trigger": "위고비"
    },
    {
      "title": "일괄약가인하 'A8 평균가 적용' 안전장치 도입 필요성 제기",
      "link": "https://www.pharmnews.com/news/articleView.html?idxno=301831",
      "pub_date": "Thu, 05 Mar 2026 06:00:00 +0900",
      "signal": "normal",
      "trigger": "약가"
    },
    {
      "title": "애경산업, 치약 금지 성분 검출에도 회수율 8%에 그쳐",
      "link": "https://mdtoday.co.kr/news/view/1065576202397210",
      "pub_date": "Thu, 05 Mar 2026 10:40:00 +0900",
      "signal": "strong",
      "trigger": "회수"
    },
    {
      "title": "베트남, '금지성분' 함유 화장품 291종 리콜…韓브랜드 포함",
      "link": "https://www.insidevina.com/news/articleView.html?idxno=42650",
      "pub_date": "Thu, 05 Mar 2026 09:16:00 +0900",
      "signal": "strong",
      "trigger": "리콜"
    },
    {
      "title": "스킨부스터 광풍속 환자안전 실종…뚫려버린 규제 사각지대",
      "link": "https://www.medicaltimes.com/Main/News/NewsView.html?ID=1167536&ref=naverpc",
      "pub_date": "Thu, 05 Mar 2026 05:30:00 +0900",
      "signal": "normal",
      "trigger": "규제"
    },
    {
      "title": "[단독] 애경 ‘금지성분 중국산 치약’ 회수율 8% 그쳐… 뒷감당은 태광...",
      "link": "https://n.news.naver.com/mnews/article/029/0003013718?sid=101",
      "pub_date": "Wed, 04 Mar 2026 11:31:00 +0900",
      "signal": "strong",
      "trigger": "회수"
    },
    {
      "title": "태광-애경, 225억 깎고 한 달 더 끌었다…'2080 리콜'이 바꾼 인수 조건",
      "link": "https://www.bizhankook.com/bk/article/31545",
      "pub_date": "Fri, 20 Feb 2026 20:00:00 +0900",
      "signal": "strong",
      "trigger": "리콜"
    },
    {
      "title": "태광산업, '치약 리콜 사태' 애경산업 인수가 낮춰",
      "link": "http://www.newsfc.co.kr/news/articleView.html?idxno=76879",
      "pub_date": "Fri, 20 Feb 2026 14:42:00 +0900",
      "signal": "strong",
      "trigger": "리콜"
    },
    {
      "title": "&quot;압타밀의 역설&quot;…유럽 리콜·직구 사각지대 논란, 강남 분유 신뢰 흔들",
      "link": "https://www.greened.kr/news/articleView.html?idxno=337045",
      "pub_date": "Sun, 15 Feb 2026 19:31:00 +0900",
      "signal": "strong",
      "trigger": "리콜"
    },
    {
      "title": "대구시약사회, 한약사·창고형 약국 규제 입법 촉구",
      "link": "https://www.yakup.com/news/index.html?mode=view&cat=17&nid=323975",
      "pub_date": "Tue, 03 Mar 2026 09:54:00 +0900",
      "signal": "normal",
      "trigger": "규제"
    },
    {
      "title": "성분명처방 공론화…건보 중심 약가개편 본격 논의",
      "link": "https://www.kpanews.co.kr/news/articleView.html?idxno=530157",
      "pub_date": "Tue, 03 Mar 2026 09:10:00 +0900",
      "signal": "normal",
      "trigger": "약가"
    },
    {
      "title": "[기자수첩] 약가 인하 움직임 좀 더 투명해질 순 없나",
      "link": "https://www.pointdaily.co.kr/news/articleView.html?idxno=294322",
      "pub_date": "Fri, 27 Feb 2026 03:56:00 +0900",
      "signal": "normal",
      "trigger": "약가"
    },
    {
      "title": "웰리렉 급여 청원 재연장...국회 복지위 3월까지 심사",
      "link": "https://www.pharmnews.com/news/articleView.html?idxno=301255",
      "pub_date": "Tue, 03 Feb 2026 05:56:00 +0900",
      "signal": "normal",
      "trigger": "급여"
    },
    {
      "title": "암보다 무서운 약값에 눈물...조기 유방암 환우, 급여화 촉구",
      "link": "https://www.pharmnews.com/news/articleView.html?idxno=300727",
      "pub_date": "Wed, 07 Jan 2026 06:00:00 +0900",
      "signal": "normal",
      "trigger": "급여"
    }
  ],
  "youtube_trends": [
    {
      "title": "같은 그릭요거트인데 \"유산균 6배 차이\"…똑똑하게 고르는 법 / SBS / 친절한 경제",
      "channel": "SBS 뉴스",
      "views": 525913,
      "published": "2026-03-04T00:58:07Z",
      "video_id": "E9WH02FP4dQ",
      "query": "유산균"
    },
    {
      "title": "이승희약사가 병원에 삐친 이유는? #최욱 #매불쇼 #이승희약사",
      "channel": "우리는 지금 매불쇼의 시대에 살고 있다",
      "views": 67624,
      "published": "2026-03-04T13:40:35Z",
      "video_id": "i1voGWaB3vk",
      "query": "약사"
    },
    {
      "title": "(반전신청사연)착한 며느리가 사준 영양제를 먹은 후, 틈만나면 쓰러져 병원에 찾아갔더니, 의사가 영양제를 보고 기함을 하며 놀라 쓰러지는데..[신청사연][사이다썰][사연라디오]",
      "channel": "사연튜브 • 사연라디오",
      "views": 37991,
      "published": "2026-03-04T12:01:10Z",
      "video_id": "ebHUvghqbCU",
      "query": "영양제"
    },
    {
      "title": "당뇨 전 단계이신가요? 식후 이거 하나 챙겨 보세요! (혈당 영양제 여주)",
      "channel": "약사가 들려주는 약 이야기",
      "views": 37895,
      "published": "2026-03-04T10:00:48Z",
      "video_id": "YpcWJtJm5Iw",
      "query": "영양제"
    },
    {
      "title": "머리카락 빠지고 눈 침침할 때? 60대 핏수 비타민 총정리 #60대건강 #시니어건강 #비타민효능 #건강정보 #탈모예방#침침한눈 #치매예방",
      "channel": "인생 조언",
      "views": 31803,
      "published": "2026-03-04T22:45:02Z",
      "video_id": "fGg8AiJfsFw",
      "query": "비타민"
    }
  ]
}